MANIFEST.in
README.md
setup.py
regression_model_module/__init__.py
regression_model_module/config.py
regression_model_module/model
regression_model_module/pre_process_pipeline
regression_model_module/predict.py
regression_model_module/preprocessors.py
regression_model_module.egg-info/PKG-INFO
regression_model_module.egg-info/SOURCES.txt
regression_model_module.egg-info/dependency_links.txt
regression_model_module.egg-info/not-zip-safe
regression_model_module.egg-info/requires.txt
regression_model_module.egg-info/top_level.txt