Metadata-Version: 2.1
Name: regression-model-module
Version: 0.0.1
Summary: An demonstration of how to create, document, and publish a python package
Home-page: https://sharabhshukla@git.fury.io/sharabhshukla/housepricemodel.git
Author: Sharabh Shukla
Author-email: andrewjcarter@gmail.com
License: MIT
Keywords: core package
Platform: UNKNOWN
Classifier: Development Status :: 3 - Alpha
Classifier: Topic :: Utilities
Classifier: License :: OSI Approved :: MIT License
Classifier: Programming Language :: Python :: 3
Classifier: Operating System :: OS Independent
